README.md
setup.py
TakeAiBLiP/AiBLiP.py
TakeAiBLiP/__init__.py
TakeAiBLiP.egg-info/PKG-INFO
TakeAiBLiP.egg-info/SOURCES.txt
TakeAiBLiP.egg-info/dependency_links.txt
TakeAiBLiP.egg-info/top_level.txt