Metadata-Version: 1.0
Name: TakeAiBLiP
Version: 0.1.6
Summary: Package to automate the intents creation, examples addition, model training, publishin and analysis in the BLiP platform
Home-page: UNKNOWN
Author: Renan Santos
Author-email: renans@take.net
License: MIT License
Keywords: BLiP NLP Ai ML Test
Platform: UNKNOWN
